README.md
setup.py
flask_soocii_auth/__init__.py
flask_soocii_auth/exceptions.py
flask_soocii_auth/users.py
soocii_services_lib/__init__.py
soocii_services_lib/auth.py
soocii_services_lib/click.py
soocii_services_lib/crypter.py
soocii_services_lib/exceptions.py
soocii_services_lib/tokens.py
soocii_services_lib/util.py
soocii_services_lib.egg-info/PKG-INFO
soocii_services_lib.egg-info/SOURCES.txt
soocii_services_lib.egg-info/dependency_links.txt
soocii_services_lib.egg-info/requires.txt
soocii_services_lib.egg-info/top_level.txt