Metadata-Version: 2.1
Name: soocii-services-lib
Version: 1.3.0
Summary: Library for Soocii back-end services which include common functions/scripts/packages.
Home-page: https://github.com/drmobile/services-lib
Author: Soocii
Author-email: service@soocii.me
License: Apache Software License
Platform: UNKNOWN
Classifier: Development Status :: 4 - Beta
Classifier: Intended Audience :: Developers
Classifier: Topic :: Software Development :: Libraries :: Python Modules
Classifier: License :: OSI Approved :: Apache Software License
Classifier: Programming Language :: Python :: 3
Classifier: Programming Language :: Python :: 3.4
Classifier: Programming Language :: Python :: 3.5
Classifier: Programming Language :: Python :: 3.6
Classifier: Programming Language :: Python :: 3.7
Provides-Extra: flask
Provides-Extra: test
Provides-Extra: doc
Provides-Extra: cli
